LICENSE
MANIFEST.in
README.md
requirements.txt
setup.py
bchelpers/__init__.py
bchelpers/exception.py
bchelpers/region.py
bchelpers/serviceendpoint.py
bchelpers.egg-info/PKG-INFO
bchelpers.egg-info/SOURCES.txt
bchelpers.egg-info/dependency_links.txt
bchelpers.egg-info/requires.txt
bchelpers.egg-info/top_level.txt