Metadata-Version: 1.1
Name: bchelpers
Version: 0.2.0
Summary: Handy helpers to make botocore easier to use
Home-page: https://github.com/garnaat/bchelpers
Author: Mitch Garnaat
Author-email: mitch@garnaat.com
License: Apache License
